odoo/addons/stock_request_employee/README.rst
odoo/addons/stock_request_employee/__init__.py
odoo/addons/stock_request_employee/__manifest__.py
odoo/addons/stock_request_employee/data/stock_location.xml
odoo/addons/stock_request_employee/i18n/stock_request_employee.pot
odoo/addons/stock_request_employee/models/__init__.py
odoo/addons/stock_request_employee/models/hr_employee.py
odoo/addons/stock_request_employee/models/procurement_rule.py
odoo/addons/stock_request_employee/models/stock_request.py
odoo/addons/stock_request_employee/models/stock_request_order.py
odoo/addons/stock_request_employee/readme/CONTRIBUTORS.rst
odoo/addons/stock_request_employee/readme/DESCRIPTION.rst
odoo/addons/stock_request_employee/readme/USAGE.rst
odoo/addons/stock_request_employee/static/description/icon.png
odoo/addons/stock_request_employee/static/description/index.html
odoo/addons/stock_request_employee/tests/__init__.py
odoo/addons/stock_request_employee/tests/test_stock_request_employee.py
odoo/addons/stock_request_employee/views/hr_employee.xml
odoo/addons/stock_request_employee/views/stock_request.xml
odoo/addons/stock_request_employee/views/stock_request_order.xml
odoo11_addon_stock_request_employee-11.0.1.0.0.99.dev3.dist-info/METADATA
odoo11_addon_stock_request_employee-11.0.1.0.0.99.dev3.dist-info/WHEEL
odoo11_addon_stock_request_employee-11.0.1.0.0.99.dev3.dist-info/top_level.txt
odoo11_addon_stock_request_employee-11.0.1.0.0.99.dev3.dist-info/RECORD
